curlconverter.py
curlconverter-1.0.0.dist-info/METADATA
curlconverter-1.0.0.dist-info/WHEEL
curlconverter-1.0.0.dist-info/RECORD
