Metadata-Version: 2.1
Name: curlconverter
Version: 1.0.0
Summary: The library is responsible for parsing a cURL request string and converting it into a Python dictionary containing the method, URL, headers, and data
Author: Dmitrii Malygin
Author-email: malygin.agency@gmail.com
Requires-Python: >=3.6,<4.0
Classifier: Programming Language :: Python :: 3
Classifier: Programming Language :: Python :: 3.6
Classifier: Programming Language :: Python :: 3.7
Classifier: Programming Language :: Python :: 3.8
Classifier: Programming Language :: Python :: 3.9
Classifier: Programming Language :: Python :: 3.10
Classifier: Programming Language :: Python :: 3.11
